ninemlcatalog/__init__.py
ninemlcatalog/base.py
ninemlcatalog/version.py
ninemlcatalog/catalog/connectionrule/AllToAll.xml
ninemlcatalog/catalog/connectionrule/Explicit.xml
ninemlcatalog/catalog/connectionrule/OneToOne.xml
ninemlcatalog/catalog/connectionrule/Probabilistic.xml
ninemlcatalog/catalog/connectionrule/RandomFanIn.xml
ninemlcatalog/catalog/connectionrule/RandomFanOut.xml
ninemlcatalog/catalog/input/ConstantRate.xml
ninemlcatalog/catalog/input/Parrot.xml
ninemlcatalog/catalog/input/Poisson.xml
ninemlcatalog/catalog/input/StepCurrent.xml
ninemlcatalog/catalog/network/Brunel2000/AI.xml
ninemlcatalog/catalog/network/Brunel2000/SIfast.xml
ninemlcatalog/catalog/network/Brunel2000/SIslow.xml
ninemlcatalog/catalog/network/Brunel2000/SR.xml
ninemlcatalog/catalog/neuron/AdaptiveExpIntegrateAndFire.xml
ninemlcatalog/catalog/neuron/HodgkinHuxley.xml
ninemlcatalog/catalog/neuron/Izhikevich.xml
ninemlcatalog/catalog/neuron/LeakyIntegrateAndFire.xml
ninemlcatalog/catalog/plasticity/Static.xml
ninemlcatalog/catalog/postsynapticresponse/Alpha.xml
ninemlcatalog/catalog/postsynapticresponse/DoubleExpCondSynapse.xml
ninemlcatalog/catalog/postsynapticresponse/ExpISyn.xml
ninemlcatalog/catalog/postsynapticresponse/Gap.xml
ninemlcatalog/catalog/postsynapticresponse/GsfaGrr.xml
ninemlcatalog/catalog/postsynapticresponse/TMGSyn.xml
ninemlcatalog/catalog/postsynapticresponse/TMISyn.xml
ninemlcatalog/catalog/randomdistribution/Bernoulli.xml
ninemlcatalog/catalog/randomdistribution/Beta.xml
ninemlcatalog/catalog/randomdistribution/Binomial.xml
ninemlcatalog/catalog/randomdistribution/Cauchy.xml
ninemlcatalog/catalog/randomdistribution/ChiSquare.xml
ninemlcatalog/catalog/randomdistribution/Dirichlet.xml
ninemlcatalog/catalog/randomdistribution/Exponential.xml
ninemlcatalog/catalog/randomdistribution/F.xml
ninemlcatalog/catalog/randomdistribution/Gamma.xml
ninemlcatalog/catalog/randomdistribution/Geometric.xml
ninemlcatalog-0.1.2.dist-info/DESCRIPTION.rst
ninemlcatalog-0.1.2.dist-info/METADATA
ninemlcatalog-0.1.2.dist-info/RECORD
ninemlcatalog-0.1.2.dist-info/WHEEL
ninemlcatalog-0.1.2.dist-info/metadata.json
ninemlcatalog-0.1.2.dist-info/top_level.txt
