Metadata-Version: 2.0
Name: ninemlcatalog
Version: 0.1.2
Summary: A collection of 9ML models and basic Python functions for accessing them
Home-page: http://nineml.net
Author: The NineML Committee
Author-email: tom.g.close@gmail.com
License: MIT Licence
Keywords: computational neuroscience modeling interoperability XML YAML JSON HDF5
Platform: UNKNOWN
Classifier: Development Status :: 4 - Beta
Classifier: Environment :: Console
Classifier: Intended Audience :: Science/Research
Classifier: License :: OSI Approved :: MIT License
Classifier: Natural Language :: English
Classifier: Operating System :: OS Independent
Classifier: Programming Language :: Python :: 2
Classifier: Programming Language :: Python :: 2.7
Classifier: Programming Language :: Python :: 3
Classifier: Programming Language :: Python :: 3.4
Classifier: Programming Language :: Python :: 3.5
Classifier: Programming Language :: Python :: 3.6
Classifier: Topic :: Scientific/Engineering
Requires-Python: >=2.7, !=3.0.*, !=3.1.*, !=3.2.*, !=3.3.*, <4
Requires-Dist: nineml (>=1.0)
Requires-Dist: future (>=0.16)
